README.md
pyshuf
setup.py
pyshuf/__init__.py
pyshuf/__main__.py
pyshuf.egg-info/PKG-INFO
pyshuf.egg-info/SOURCES.txt
pyshuf.egg-info/dependency_links.txt
pyshuf.egg-info/entry_points.txt
pyshuf.egg-info/top_level.txt