Metadata-Version: 1.0
Name: pyshuf
Version: 0.0.1
Summary: Inexact clone of GNU shuf. Shuffles order of lines in a file.
Home-page: https://github.org/jakekara/pyshuf
Author: Jake Kara
Author-email: UNKNOWN
License: GPL-3
Keywords: shuf
Platform: UNKNOWN
